AbeewayConfig/CSVFile.py
AbeewayConfig/Config.py
AbeewayConfig/CustomGUI.py
AbeewayConfig/Device.py
AbeewayConfig/GUI_setup.py
AbeewayConfig/__init__.py
AbeewayConfig/abeewayconfig.py
AbeewayConfig/smartbadgecfgdict.py
AbeewayConfig-1.1.2.dist-info/LICENSE
AbeewayConfig-1.1.2.dist-info/METADATA
AbeewayConfig-1.1.2.dist-info/WHEEL
AbeewayConfig-1.1.2.dist-info/entry_points.txt
AbeewayConfig-1.1.2.dist-info/top_level.txt
AbeewayConfig-1.1.2.dist-info/RECORD
