Metadata-Version: 2.1
Name: AbeewayConfig
Version: 1.1.2
Summary: Abeeway configuration tool
Home-page: https://github.com/jlabbude/AbeewayConfig
Author: João Lucas
Classifier: Development Status :: 3 - Alpha
Classifier: Programming Language :: Python :: 3
Requires-Python: >=3.0
License-File: LICENSE
Requires-Dist: pyserial
Requires-Dist: tk
Requires-Dist: requests
Requires-Dist: typing-extensions
Requires-Dist: serialmanager
